Metadata-Version: 1.0
Name: reb-probability
Version: 0.1
Summary: Gaussian and Binomial distributions
Home-page: UNKNOWN
Author: Roy Berg
Author-email: UNKNOWN
License: UNKNOWN
Platform: UNKNOWN
